kbana/__init__.py
kbana/wrapper.py
kbana/analysis/__init__.py
kbana/analysis/key_analysis.py
kbana/analysis/__pycache__/__init__.cpython-39.pyc
kbana/analysis/__pycache__/key_analysis.cpython-39.pyc
kbana/analysis/keyboard_styles/key_plot_map_meta.txt
kbana/analysis/keyboard_styles/MainType/Thai_Pattachaot_shift/key_plot_map.json
kbana/analysis/keyboard_styles/MainType/Thai_Pattachaot_shift/pattachoat_shift.png
kbana/analysis/keyboard_styles/MainType/Thai_Pattachoat_no_shift/key_plot_map.json
kbana/analysis/keyboard_styles/MainType/Thai_Pattachoat_no_shift/pattachoat_no_shift.png
kbana/analysis/keyboard_styles/MainType/blank/blank.png
kbana/analysis/keyboard_styles/MainType/blank/key_plot_map.json
kbana/analysis/maps/finger_scode_map.json
kbana/analysis/maps/scode_name_map.json
kbana/analysis/maps/shift_key_name_map.json
kbana/analysis/misc/hands.png
kbana/capture/__init__.py
kbana/capture/keyboard_capture.py
kbana/capture/__pycache__/__init__.cpython-39.pyc
kbana/capture/__pycache__/keyboard_capture.cpython-39.pyc
kbana/capture/misc/win-language-id.json
kbana-0.1.2.dist-info/LICENSE
kbana-0.1.2.dist-info/METADATA
kbana-0.1.2.dist-info/WHEEL
kbana-0.1.2.dist-info/top_level.txt
kbana-0.1.2.dist-info/RECORD
